{"projects":[{"geometry":{"type":"Polygon","coordinates":[[[-52.999769,-29.520189,0],[-52.998947,-29.520189,0],[-52.998947,-29.521083,0],[-52.998717,-29.521083,0],[-52.998717,-29.521614,0],[-52.999411,-29.521614,0],[-52.999411,-29.521192,0],[-52.999769,-29.521192,0],[-52.999769,-29.520189,0]]],"centerPoint":[-52.99927082795846,-29.52088282263347]},"processo":"810583/2019","numero":"810583","ano":"2019","area_ha":"1,23","id":"{3F841991-9260-4CE6-AB25-2E9A0F1AC266}","fase":"REGISTRO DE EXTRAÇÃO","ultimo_evento":"923 - REG EXT/REGISTRO DE EXTRAÇÃO 04 ANOS PUBLICADO EM 20/02/2020","modified":"2020/02/20","titular":"Prefeitura Municipal de Lagoa Bonita do Sul","substancia":"BASALTO","uso":"Pedra de talhe","uf":"RS","processo_minerario":"810.583/2019","fase_slug":"registro_de_extracao","fase_id":11,"substance_slug":"basalto","municipality":"Lagoa Bonita do Sul, Passa Sete"},{"geometry":{"type":"Polygon","coordinates":[[[-53.03502,-29.511856,0],[-53.032734,-29.511856,0],[-53.032734,-29.513698,0],[-53.035023,-29.513698,0],[-53.035023,-29.511856,0],[-53.03502,-29.511856,0]]],"centerPoint":[-53.0338785,-29.512777]},"processo":"811053/2014","numero":"811053","ano":"2014","area_ha":"4,53","id":"{2342AA97-150E-45F0-B87A-735371F6AE62}","fase":"REGISTRO DE EXTRAÇÃO","ultimo_evento":"1305 - REG EXT/BAIXA TRANSCRIÇÃO DO REGISTRO EXTRAÇÃO EM 13/06/2019","modified":"2019/06/13","titular":"Prefeitura Municipal de Lagoa Bonita do Sul","substancia":"CASCALHO","uso":"Brita","uf":"RS","processo_minerario":"811.053/2014","fase_slug":"registro_de_extracao","fase_id":11,"substance_slug":"cascalho","municipality":"Agudo, Lagoa Bonita do Sul"},{"geometry":{"type":"Polygon","coordinates":[[[-53.008944,-29.534222,0],[-53.008944,-29.53465,0],[-53.00885,-29.53465,0],[-53.00885,-29.535047,0],[-53.009872,-29.535047,0],[-53.009872,-29.534717,0],[-53.009939,-29.534717,0],[-53.009939,-29.534328,0],[-53.009506,-29.534328,0],[-53.009506,-29.534275,0],[-53.009314,-29.534275,0],[-53.009314,-29.534222,0],[-53.008944,-29.534222,0]]],"centerPoint":[-53.0093906084683,-29.534666383639852]},"processo":"810160/2017","numero":"810160","ano":"2017","area_ha":"0,84","id":"{C6E3715C-4BF8-46DB-9E45-CCB6D5642FBB}","fase":"REGISTRO DE EXTRAÇÃO","ultimo_evento":"923 - REG EXT/REGISTRO DE EXTRAÇÃO 04 ANOS PUBLICADO EM 04/01/2018","modified":"2018/01/04","titular":"Prefeitura Municipal de Lagoa Bonita do Sul","substancia":"SAIBRO","uso":"Construção civil","uf":"RS","processo_minerario":"810.160/2017","fase_slug":"registro_de_extracao","fase_id":11,"substance_slug":"saibro","municipality":"Cerro Branco, Lagoa Bonita do Sul"},{"geometry":{"type":"Polygon","coordinates":[[[-53.049161,-29.453225,0],[-53.048322,-29.453225,0],[-53.048322,-29.453853,0],[-53.049161,-29.453853,0],[-53.049161,-29.453225,0]]],"centerPoint":[-53.0487415,-29.453539]},"processo":"810629/2016","numero":"810629","ano":"2016","area_ha":"0,57","id":"{377FDCAC-155E-4AE5-8AA2-E0FB097AC92D}","fase":"LICENCIAMENTO","ultimo_evento":"730 - LICEN/LICENCIAMENTO AUTORIZADO PUBLICADO EM 21/09/2016","modified":"2016/09/21","titular":"Marcelino Neves Selli Me","substancia":"BASALTO","uso":"Pedra de talhe","uf":"RS","processo_minerario":"810.629/2016","fase_slug":"licenciamento","fase_id":9,"substance_slug":"basalto","municipality":"Agudo, Lagoa Bonita do Sul, Sobradinho"},{"geometry":{"type":"Polygon","coordinates":[[[-53.055564,-29.496544,0],[-53.054011,-29.496544,0],[-53.054011,-29.497542,0],[-53.055603,-29.497542,0],[-53.055603,-29.496544,0],[-53.055564,-29.496544,0]]],"centerPoint":[-53.054807,-29.497042999999998]},"processo":"810705/2015","numero":"810705","ano":"2015","area_ha":"1,71","id":"{40484E47-46F5-4F0B-8382-0079759B141A}","fase":"REGISTRO DE EXTRAÇÃO","ultimo_evento":"923 - REG EXT/REGISTRO DE EXTRAÇÃO 04 ANOS PUBLICADO EM 12/01/2016","modified":"2016/01/12","titular":"Prefeitura Municipal de Lagoa Bonita do Sul","substancia":"AREIA","uso":"Construção civil","uf":"RS","processo_minerario":"810.705/2015","fase_slug":"registro_de_extracao","fase_id":11,"substance_slug":"areia","municipality":"Agudo, Lagoa Bonita do Sul"},{"geometry":{"type":"Polygon","coordinates":[[[-53.091901,-29.5023,0],[-53.091901,-29.502011,0],[-53.090637,-29.502011,0],[-53.090637,-29.503203,0],[-53.091901,-29.503203,0],[-53.091901,-29.5023,0]]],"centerPoint":[-53.091269,-29.502606999999998]},"processo":"811054/2014","numero":"811054","ano":"2014","area_ha":"1,62","id":"{4D4BC85A-5C13-4A08-9907-62DF36AF8B28}","fase":"REGISTRO DE EXTRAÇÃO","ultimo_evento":"923 - REG EXT/REGISTRO DE EXTRAÇÃO 04 ANOS PUBLICADO EM 12/06/2015","modified":"2015/06/12","titular":"Prefeitura Municipal de Lagoa Bonita do Sul","substancia":"BASALTO","uso":"Brita","uf":"RS","processo_minerario":"811.054/2014","fase_slug":"registro_de_extracao","fase_id":11,"substance_slug":"basalto","municipality":"Agudo, Lagoa Bonita do Sul"},{"geometry":{"type":"Polygon","coordinates":[[[-53.049686,-29.45415,0],[-53.049686,-29.4537,0],[-53.048864,-29.4537,0],[-53.048864,-29.454345,0],[-53.049686,-29.454345,0],[-53.049686,-29.45415,0]]],"centerPoint":[-53.049275,-29.4540225]},"processo":"810751/2014","numero":"810751","ano":"2014","area_ha":"0,57","id":"{9FB41DCB-1950-44C8-BA10-A87D23665C19}","fase":"REQUERIMENTO DE LICENCIAMENTO","ultimo_evento":"1281 - REQ LICEN/INDEFERIMENTO SEM ONERAÇÃO PORT 266/2008 EM 15/09/2014","modified":"2014/09/15","titular":"Marcelino Neves Selli Me","substancia":"BASALTO","uso":"Brita","uf":"RS","processo_minerario":"810.751/2014","fase_slug":"requerimento_de_licenciamento","fase_id":8,"substance_slug":"basalto","municipality":"Agudo, Lagoa Bonita do Sul, Sobradinho"}]}