{"projects":[{"geometry":{"type":"Polygon","coordinates":[[[-51.995579,-27.951896,0],[-51.998628,-27.951896,0],[-51.998628,-27.949189,0],[-51.995579,-27.949189,0],[-51.995579,-27.951896,0]]],"centerPoint":[-51.997103499999994,-27.9505425]},"processo":"810073/2004","id":"{35D51CB8-5F81-465E-BADA-D90CAAB38FA5}","numero":"810073","ano":"2004","area_ha":"9","fase":"LICENCIAMENTO","ultimo_evento":"736 - LICEN/DOCUMENTO DIVERSO PROTOCOLIZADO EM 16/11/2020","modified":"2020/11/16","titular":"Csl Construtora Sacchi S.a.","substancia":"BASALTO","uso":"Construção civil","uf":"RS","fase_slug":"licenciamento","fase_id":9,"substance_slug":"basalto","municipality":"Charrua"},{"geometry":{"type":"Polygon","coordinates":[[[-52.002328,-27.954422,0],[-52.002328,-27.955461,0],[-52.000625,-27.955461,0],[-52.000625,-27.959003,0],[-52.001278,-27.959003,0],[-52.001278,-27.960475,0],[-52.003964,-27.960475,0],[-52.003964,-27.959714,0],[-52.003604,-27.959714,0],[-52.003604,-27.959259,0],[-52.003273,-27.959259,0],[-52.003273,-27.958376,0],[-52.003594,-27.958376,0],[-52.003594,-27.958168,0],[-52.005777,-27.958168,0],[-52.005777,-27.959714,0],[-52.005792,-27.959714,0],[-52.005792,-27.957411,0],[-52.004528,-27.957411,0],[-52.004528,-27.955375,0],[-52.004528,-27.954422,0],[-52.002328,-27.954422,0]]],"centerPoint":[-52.00272601986062,-27.957393819201105]},"processo":"300939/2019","id":"{F1C80847-B217-462D-B5D9-9A5C1CA7DEB7}","numero":"300939","ano":"2019","area_ha":"21,5","fase":"DISPONIBILIDADE","ultimo_evento":"1828 - DISPONIB/ÁREA DESCARTADA LIBERADA PARA EDITAL EM 17/09/2020","modified":"2020/09/17","titular":"DADO NÃO CADASTRADO","substancia":"DADO NÃO CADASTRADO","uso":"DADO NÃO CADASTRADO","uf":"DADO NÃO CADASTRADO","fase_slug":"disponibilidade","fase_id":14,"substance_slug":"dado_nao_cadastrado","municipality":"Charrua"},{"geometry":{"type":"Polygon","coordinates":[[[-52.002328,-27.954422,0],[-52.002328,-27.955461,0],[-52.000625,-27.955461,0],[-52.000625,-27.959003,0],[-52.001278,-27.959003,0],[-52.001278,-27.960475,0],[-52.003964,-27.960475,0],[-52.003964,-27.959714,0],[-52.005792,-27.959714,0],[-52.005792,-27.957411,0],[-52.004528,-27.957411,0],[-52.004528,-27.955375,0],[-52.004528,-27.954422,0],[-52.002328,-27.954422,0]]],"centerPoint":[-52.003017618963,-27.95763420511647]},"processo":"810473/2018","id":"{F1C80847-B217-462D-B5D9-9A5C1CA7DEB7}","numero":"810473","ano":"2018","area_ha":"25,49","fase":"AUTORIZAÇÃO DE PESQUISA","ultimo_evento":"264 - AUT PESQ/PAGAMENTO TAH EFETUADO EM 17/01/2020","modified":"2020/01/17","titular":"Csl Construtora Sacchi S.a.","substancia":"BASALTO","uso":"Brita","uf":"RS","fase_slug":"autorizacao_de_pesquisa","fase_id":2,"substance_slug":"basalto","municipality":"Charrua"},{"geometry":{"type":"Polygon","coordinates":[[[-52.005777,-27.958168,0],[-52.003594,-27.958168,0],[-52.003594,-27.958376,0],[-52.003273,-27.958376,0],[-52.003273,-27.959259,0],[-52.003604,-27.959259,0],[-52.003604,-27.959714,0],[-52.005777,-27.959714,0],[-52.005777,-27.958168,0]]],"centerPoint":[-52.004525,-27.958941000000003]},"processo":"810468/2019","id":"{A4B6CD1D-4E56-4CEE-A5AD-A5C4F856BA51}","numero":"810468","ano":"2019","area_ha":"3,99","fase":"LICENCIAMENTO","ultimo_evento":"730 - LICEN/LICENCIAMENTO AUTORIZADO PUBLICADO EM 11/12/2019","modified":"2019/12/11","titular":"Csl Construtora Sacchi S.a.","substancia":"BASALTO","uso":"Brita","uf":"RS","fase_slug":"licenciamento","fase_id":9,"substance_slug":"basalto","municipality":"Charrua"},{"geometry":{"type":"Polygon","coordinates":[[[-51.956525,-27.916978,0],[-51.955967,-27.916978,0],[-51.955967,-27.917461,0],[-51.956525,-27.917461,0],[-51.956525,-27.916978,0]]],"centerPoint":[-51.956246,-27.9172195]},"processo":"811539/2013","id":"{797FEE7C-C067-4CEE-B9FB-86DE18316296}","numero":"811539","ano":"2013","area_ha":"0,29","fase":"REGISTRO DE EXTRAÇÃO","ultimo_evento":"926 - REG EXT/PRORROGAÇÃO DO PRAZO POR 04 ANOS EM 15/07/2019","modified":"2019/07/15","titular":"Prefeitura Municipal de Charrua","substancia":"SAIBRO","uso":"Construção civil","uf":"RS","fase_slug":"registro_de_extracao","fase_id":11,"substance_slug":"saibro","municipality":"Charrua, Sananduva"},{"geometry":{"type":"Polygon","coordinates":[[[-52.080488,-27.970419,0],[-52.079794,-27.970419,0],[-52.079794,-27.972063,0],[-52.080488,-27.972063,0],[-52.080488,-27.970419,0]]],"centerPoint":[-52.080141,-27.971241]},"processo":"811540/2013","id":"{0FC0AFE9-6736-4054-8044-FFCE495584EA}","numero":"811540","ano":"2013","area_ha":"1,24","fase":"REGISTRO DE EXTRAÇÃO","ultimo_evento":"926 - REG EXT/PRORROGAÇÃO DO PRAZO POR 04 ANOS EM 15/07/2019","modified":"2019/07/15","titular":"Prefeitura Municipal de Charrua","substancia":"SAIBRO","uso":"Construção civil","uf":"RS","fase_slug":"registro_de_extracao","fase_id":11,"substance_slug":"saibro","municipality":"Charrua, Getúlio Vargas"},{"geometry":{"type":"Polygon","coordinates":[[[-52.006172,-27.954792,0],[-52.005253,-27.954792,0],[-52.005253,-27.955375,0],[-52.004528,-27.955375,0],[-52.004528,-27.957411,0],[-52.006639,-27.957411,0],[-52.006639,-27.955936,0],[-52.006172,-27.955936,0],[-52.006172,-27.954792,0]]],"centerPoint":[-52.0055835,-27.9563555]},"processo":"810072/2018","id":"{4E579F76-C585-44BE-9614-23E0D69AEF1A}","numero":"810072","ano":"2018","area_ha":"4,99","fase":"AUTORIZAÇÃO DE PESQUISA","ultimo_evento":"264 - AUT PESQ/PAGAMENTO TAH EFETUADO EM 03/07/2019","modified":"2019/07/03","titular":"Csl Construtora Sacchi S.a.","substancia":"BASALTO","uso":"Brita","uf":"RS","fase_slug":"autorizacao_de_pesquisa","fase_id":2,"substance_slug":"basalto","municipality":"Charrua"},{"geometry":{"type":"Polygon","coordinates":[[[-51.995579,-27.948056,0],[-51.995579,-27.949189,0],[-51.998628,-27.949189,0],[-51.998628,-27.951896,0],[-51.995579,-27.951896,0],[-51.995579,-27.953972,0],[-52.001944,-27.953972,0],[-52.001944,-27.948056,0],[-51.995579,-27.948056,0]]],"centerPoint":[-51.999226787764165,-27.95114628100822]},"processo":"810279/2017","id":"{C5D95959-3D10-459D-A4BE-C9E198AD8F02}","numero":"810279","ano":"2017","area_ha":"32,07","fase":"AUTORIZAÇÃO DE PESQUISA","ultimo_evento":"265 - AUT PESQ/PRORROGAÇÃO PRAZO ALVARÁ SOLICITADO EM 13/05/2019","modified":"2019/05/13","titular":"Csl Construtora Sacchi S.a.","substancia":"BASALTO","uso":"Brita","uf":"RS","fase_slug":"autorizacao_de_pesquisa","fase_id":2,"substance_slug":"basalto","municipality":"Charrua"},{"geometry":{"type":"Polygon","coordinates":[[[-52.045574,-27.961775,0],[-52.044978,-27.961775,0],[-52.044978,-27.962511,0],[-52.045574,-27.962511,0],[-52.045574,-27.961775,0]]],"centerPoint":[-52.045276,-27.962142999999998]},"processo":"811535/2013","id":"{09FF9B09-3434-405C-AAE3-C76D238F3D72}","numero":"811535","ano":"2013","area_ha":"0,48","fase":"REGISTRO DE EXTRAÇÃO","ultimo_evento":"923 - REG EXT/REGISTRO DE EXTRAÇÃO 04 ANOS PUBLICADO EM 09/05/2014","modified":"2014/05/09","titular":"Prefeitura Municipal de Charrua","substancia":"SAIBRO","uso":"Construção civil","uf":"RS","fase_slug":"registro_de_extracao","fase_id":11,"substance_slug":"saibro","municipality":"Charrua"},{"geometry":{"type":"Polygon","coordinates":[[[-51.988188,-27.99585,0],[-51.987534,-27.99585,0],[-51.987534,-27.996451,0],[-51.988188,-27.996451,0],[-51.988188,-27.99585,0]]],"centerPoint":[-51.987860999999995,-27.9961505]},"processo":"811537/2013","id":"{572F26AE-E3A6-4851-B92C-230EF04E9F19}","numero":"811537","ano":"2013","area_ha":"0,43","fase":"REGISTRO DE EXTRAÇÃO","ultimo_evento":"923 - REG EXT/REGISTRO DE EXTRAÇÃO 04 ANOS PUBLICADO EM 09/05/2014","modified":"2014/05/09","titular":"Prefeitura Municipal de Charrua","substancia":"SAIBRO","uso":"Construção civil","uf":"RS","fase_slug":"registro_de_extracao","fase_id":11,"substance_slug":"saibro","municipality":"Charrua, Tapejara"},{"geometry":{"type":"Polygon","coordinates":[[[-52.006461,-27.90392,0],[-52.005874,-27.90392,0],[-52.005874,-27.904803,0],[-52.006461,-27.904803,0],[-52.006461,-27.90392,0]]],"centerPoint":[-52.006167500000004,-27.9043615]},"processo":"811541/2013","id":"{554D216A-322F-4678-B67B-C36B23A352D4}","numero":"811541","ano":"2013","area_ha":"0,57","fase":"REGISTRO DE EXTRAÇÃO","ultimo_evento":"923 - REG EXT/REGISTRO DE EXTRAÇÃO 04 ANOS PUBLICADO EM 25/04/2014","modified":"2014/04/25","titular":"Prefeitura Municipal de Charrua","substancia":"SAIBRO","uso":"Construção civil","uf":"RS","fase_slug":"registro_de_extracao","fase_id":11,"substance_slug":"saibro","municipality":"Charrua, Floriano Peixoto"},{"geometry":{"type":"Polygon","coordinates":[[[-51.964949,-27.894652,0],[-51.964379,-27.894652,0],[-51.964379,-27.895927,0],[-51.964949,-27.895927,0],[-51.964949,-27.894652,0]]],"centerPoint":[-51.964664,-27.8952895]},"processo":"811538/2013","id":"{E476E523-C08E-4B19-9C38-B4B44EB47F42}","numero":"811538","ano":"2013","area_ha":"0,79","fase":"REGISTRO DE EXTRAÇÃO","ultimo_evento":"923 - REG EXT/REGISTRO DE EXTRAÇÃO 04 ANOS PUBLICADO EM 25/04/2014","modified":"2014/04/25","titular":"Prefeitura Municipal de Charrua","substancia":"SAIBRO","uso":"Construção civil","uf":"RS","fase_slug":"registro_de_extracao","fase_id":11,"substance_slug":"saibro","municipality":"Charrua, Floriano Peixoto"},{"geometry":{"type":"Polygon","coordinates":[[[-51.966846,-27.982862,0],[-51.965892,-27.982862,0],[-51.965892,-27.983889,0],[-51.966846,-27.983889,0],[-51.966846,-27.982862,0]]],"centerPoint":[-51.966369,-27.9833755]},"processo":"811534/2013","id":"{1654197A-8795-48D2-B5DC-D09F5B3131BF}","numero":"811534","ano":"2013","area_ha":"1,07","fase":"REGISTRO DE EXTRAÇÃO","ultimo_evento":"923 - REG EXT/REGISTRO DE EXTRAÇÃO 04 ANOS PUBLICADO EM 25/04/2014","modified":"2014/04/25","titular":"Prefeitura Municipal de Charrua","substancia":"SAIBRO","uso":"Construção civil","uf":"RS","fase_slug":"registro_de_extracao","fase_id":11,"substance_slug":"saibro","municipality":"Charrua, Tapejara"},{"geometry":{"type":"Polygon","coordinates":[[[-52.039626,-27.931709,0],[-52.038781,-27.931709,0],[-52.038781,-27.932331,0],[-52.039626,-27.932331,0],[-52.039626,-27.931709,0]]],"centerPoint":[-52.0392035,-27.93202]},"processo":"811536/2013","id":"{93F27926-8C58-4003-BD8D-08788D959175}","numero":"811536","ano":"2013","area_ha":"0,57","fase":"REGISTRO DE EXTRAÇÃO","ultimo_evento":"923 - REG EXT/REGISTRO DE EXTRAÇÃO 04 ANOS PUBLICADO EM 25/04/2014","modified":"2014/04/25","titular":"Prefeitura Municipal de Charrua","substancia":"SAIBRO","uso":"Construção civil","uf":"RS","fase_slug":"registro_de_extracao","fase_id":11,"substance_slug":"saibro","municipality":"Charrua"},{"geometry":{"type":"Polygon","coordinates":[[[-51.992217,-27.927553,0],[-51.990795,-27.927553,0],[-51.990795,-27.928827,0],[-51.992217,-27.928827,0],[-51.992217,-27.927553,0]]],"centerPoint":[-51.991506,-27.92819]},"processo":"811093/2013","id":"{185945CA-2278-4C62-851B-195D38282656}","numero":"811093","ano":"2013","area_ha":"1,98","fase":"REGISTRO DE EXTRAÇÃO","ultimo_evento":"924 - REG EXT/REGISTRO DE EXTRAÇÃO 05 ANOS PUBLICADO EM 23/12/2013","modified":"2013/12/23","titular":"Prefeitura Municipal de Charrua","substancia":"SAIBRO","uso":"Construção civil","uf":"RS","fase_slug":"registro_de_extracao","fase_id":11,"substance_slug":"saibro","municipality":"Charrua"},{"geometry":{"type":"Polygon","coordinates":[[[-52.000463,-27.969648,0],[-51.999216,-27.969648,0],[-51.999216,-27.970832,0],[-52.000463,-27.970832,0],[-52.000463,-27.969648,0]]],"centerPoint":[-51.9998395,-27.97024]},"processo":"810362/2013","id":"{4CCCE296-C696-4125-8E45-F24557EDD384}","numero":"810362","ano":"2013","area_ha":"1,61","fase":"REGISTRO DE EXTRAÇÃO","ultimo_evento":"924 - REG EXT/REGISTRO DE EXTRAÇÃO 05 ANOS PUBLICADO EM 23/05/2013","modified":"2013/05/23","titular":"Prefeitura Municipal de Charrua","substancia":"SAIBRO","uso":"Construção civil","uf":"RS","fase_slug":"registro_de_extracao","fase_id":11,"substance_slug":"saibro","municipality":"Charrua"}]}