{"projects":[{"geometry":{"type":"Polygon","coordinates":[[[-52.907267,-28.702152,0],[-52.907267,-28.707768,0],[-52.91415,-28.707768,0],[-52.91415,-28.702152,0],[-52.911327,-28.702152,0],[-52.911327,-28.703567,0],[-52.911906,-28.703567,0],[-52.911906,-28.705836,0],[-52.909817,-28.705836,0],[-52.909817,-28.703873,0],[-52.910745,-28.703873,0],[-52.910745,-28.703567,0],[-52.911324,-28.703567,0],[-52.911324,-28.702152,0],[-52.907267,-28.702152,0]]],"centerPoint":[-52.911342,-28.70496]},"processo":"300851/2020","id":"{F03BCEDA-BA25-4060-A6E7-8FD3A6E492D9}","numero":"300851","ano":"2020","area_ha":"37,04","fase":"DISPONIBILIDADE","ultimo_evento":"1828 - DISPONIB/ÁREA DESCARTADA LIBERADA PARA EDITAL EM 07/03/2021","modified":"2021/03/07","titular":"DADO NÃO CADASTRADO","substancia":"DADO NÃO CADASTRADO","uso":"DADO NÃO CADASTRADO","uf":"DADO NÃO CADASTRADO","fase_slug":"disponibilidade","fase_id":14,"substance_slug":"dado_nao_cadastrado","municipality":"Espumoso, Tapera"},{"geometry":{"type":"Polygon","coordinates":[[[-52.910745,-28.703567,0],[-52.910745,-28.703873,0],[-52.909817,-28.703873,0],[-52.909817,-28.705836,0],[-52.911906,-28.705836,0],[-52.911906,-28.703567,0],[-52.910745,-28.703567,0]]],"centerPoint":[-52.910861499999996,-28.7047915]},"processo":"810512/2020","id":"{8370511B-E88B-4F32-9AB8-6CB0F5D17BCF}","numero":"810512","ano":"2020","area_ha":"4,82","fase":"LICENCIAMENTO","ultimo_evento":"730 - LICEN/LICENCIAMENTO AUTORIZADO PUBLICADO EM 21/09/2020","modified":"2020/09/21","titular":"F. F. CONSTRUTORA SIGNOR LTDA","substancia":"BASALTO","uso":"Brita","uf":"RS","fase_slug":"licenciamento","fase_id":9,"substance_slug":"basalto","municipality":"Espumoso, Tapera"},{"geometry":{"type":"Polygon","coordinates":[[[-52.91415,-28.702152,0],[-52.907267,-28.702152,0],[-52.907267,-28.707768,0],[-52.91415,-28.707768,0],[-52.91415,-28.702152,0]]],"centerPoint":[-52.9107085,-28.70496]},"processo":"810841/2018","id":"{F03BCEDA-BA25-4060-A6E7-8FD3A6E492D9}","numero":"810841","ano":"2018","area_ha":"41,87","fase":"AUTORIZAÇÃO DE PESQUISA","ultimo_evento":"279 - AUT PESQ/ARQUIVAMENTO PROCESSO PUBLICADO EM 21/09/2020","modified":"2020/09/21","titular":"F. F. CONSTRUTORA SIGNOR LTDA","substancia":"ARGILA","uso":"Construção civil","uf":"RS","fase_slug":"autorizacao_de_pesquisa","fase_id":2,"substance_slug":"argila","municipality":"Espumoso, Tapera"},{"geometry":{"type":"Polygon","coordinates":[[[-52.863192,-28.695685,0],[-52.863192,-28.696081,0],[-52.862943,-28.696081,0],[-52.862943,-28.696583,0],[-52.86368,-28.696583,0],[-52.86368,-28.696364,0],[-52.863995,-28.696364,0],[-52.863995,-28.696165,0],[-52.863777,-28.696165,0],[-52.863777,-28.695959,0],[-52.863719,-28.695959,0],[-52.863719,-28.695837,0],[-52.863648,-28.695837,0],[-52.863648,-28.695685,0],[-52.863192,-28.695685,0]]],"centerPoint":[-52.863469,-28.696134]},"processo":"810109/2019","id":"{6D09A931-F16D-4BD2-AAB9-0A797F85543B}","numero":"810109","ano":"2019","area_ha":"0,7","fase":"REQUERIMENTO DE REGISTRO DE EXTRAÇÃO","ultimo_evento":"830 - REQ EXT/INDEFERIMENTO NÃO CUMPRIMENTO DE EXIGÊNCIA EM 18/09/2019","modified":"2019/09/18","titular":"MUNICIPIO DE TAPERA","substancia":"BASALTO","uso":"Brita","uf":"RS","fase_slug":"requerimento_de_registro_de_extracao","fase_id":10,"substance_slug":"basalto","municipality":"Espumoso, Tapera"},{"geometry":{"type":"Polygon","coordinates":[[[-52.899851,-28.595641,0],[-52.899851,-28.59581,0],[-52.899755,-28.59581,0],[-52.899755,-28.595955,0],[-52.899683,-28.595955,0],[-52.899683,-28.596047,0],[-52.899635,-28.596047,0],[-52.899635,-28.59618,0],[-52.899571,-28.59618,0],[-52.899571,-28.596296,0],[-52.899517,-28.596296,0],[-52.899517,-28.597014,0],[-52.899581,-28.597014,0],[-52.899581,-28.597129,0],[-52.899688,-28.597129,0],[-52.899688,-28.597337,0],[-52.899735,-28.597337,0],[-52.899735,-28.596631,0],[-52.900655,-28.596631,0],[-52.900655,-28.597335,0],[-52.900656,-28.597335,0],[-52.900656,-28.597103,0],[-52.900766,-28.597103,0],[-52.900766,-28.59692,0],[-52.900847,-28.59692,0],[-52.900847,-28.595641,0],[-52.899851,-28.595641,0]]],"centerPoint":[-52.90021569186769,-28.596258904533574]},"processo":"810110/2019","id":"{B7940B56-A753-4FC8-A0F7-822930229095}","numero":"810110","ano":"2019","area_ha":"1,49","fase":"REQUERIMENTO DE REGISTRO DE EXTRAÇÃO","ultimo_evento":"820 - REQ EXT/REQUERIMENTO PROTOCOLIZADO EM 01/04/2019","modified":"2019/04/01","titular":"MUNICIPIO DE TAPERA","substancia":"BASALTO","uso":"Brita","uf":"RS","fase_slug":"requerimento_de_registro_de_extracao","fase_id":10,"substance_slug":"basalto","municipality":"Lagoa dos Três Cantos, Tapera"},{"geometry":{"type":"Polygon","coordinates":[[[-52.900479,-28.597764,0],[-52.900541,-28.597764,0],[-52.900541,-28.597647,0],[-52.900479,-28.597647,0],[-52.900479,-28.597764,0]]],"centerPoint":[-52.90051,-28.5977055]},"processo":"810110/2019","id":"{1E4A3751-BAE4-401E-BAFF-71542E54E102}","numero":"810110","ano":"2019","area_ha":"0,01","fase":"REQUERIMENTO DE REGISTRO DE EXTRAÇÃO","ultimo_evento":"820 - REQ EXT/REQUERIMENTO PROTOCOLIZADO EM 01/04/2019","modified":"2019/04/01","titular":"MUNICIPIO DE TAPERA","substancia":"BASALTO","uso":"Brita","uf":"RS","fase_slug":"requerimento_de_registro_de_extracao","fase_id":10,"substance_slug":"basalto","municipality":"Lagoa dos Três Cantos, Tapera"},{"geometry":{"type":"Polygon","coordinates":[[[-52.920378,-28.650442,0],[-52.920378,-28.651484,0],[-52.921075,-28.651484,0],[-52.921075,-28.650442,0],[-52.920378,-28.650442,0]]],"centerPoint":[-52.9207265,-28.650963]},"processo":"810162/2018","id":"{B2922423-3542-4790-852F-E1E082B07510}","numero":"810162","ano":"2018","area_ha":"0,79","fase":"REQUERIMENTO DE REGISTRO DE EXTRAÇÃO","ultimo_evento":"830 - REQ EXT/INDEFERIMENTO NÃO CUMPRIMENTO DE EXIGÊNCIA EM 31/07/2018","modified":"2018/07/31","titular":"MUNICIPIO DE TAPERA","substancia":"SAIBRO","uso":"Construção civil","uf":"RS","fase_slug":"requerimento_de_registro_de_extracao","fase_id":10,"substance_slug":"saibro","municipality":"Espumoso, Selbach, Tapera"},{"geometry":{"type":"Polygon","coordinates":[[[-52.900655,-28.596631,0],[-52.899735,-28.596631,0],[-52.899735,-28.597647,0],[-52.900655,-28.597647,0],[-52.900655,-28.596631,0]]],"centerPoint":[-52.900195,-28.597139]},"processo":"811175/2013","id":"{BB3922AE-15F5-416D-955D-459B32B77E7E}","numero":"811175","ano":"2013","area_ha":"1,01","fase":"REGISTRO DE EXTRAÇÃO","ultimo_evento":"940 - REG EXT/PRORROGAÇÃO DO PRAZO POR 02 ANOS EM 02/06/2017","modified":"2017/06/02","titular":"MUNICIPIO DE TAPERA","substancia":"SAIBRO","uso":"Construção civil","uf":"RS","fase_slug":"registro_de_extracao","fase_id":11,"substance_slug":"saibro","municipality":"Lagoa dos Três Cantos, Tapera"},{"geometry":{"type":"Polygon","coordinates":[[[-52.772547,-28.594945,0],[-52.772547,-28.593817,0],[-52.77173,-28.593817,0],[-52.77173,-28.594945,0],[-52.772547,-28.594945,0]]],"centerPoint":[-52.7721385,-28.594381]},"processo":"811643/2014","id":"{29636D58-8472-47B1-A9BA-40DAAECD68C7}","numero":"811643","ano":"2014","area_ha":"1","fase":"REGISTRO DE EXTRAÇÃO","ultimo_evento":"923 - REG EXT/REGISTRO DE EXTRAÇÃO 04 ANOS PUBLICADO EM 27/04/2015","modified":"2015/04/27","titular":"Municipio de Lagoa dos Tres Cantos","substancia":"SAIBRO","uso":"Construção civil","uf":"RS","fase_slug":"registro_de_extracao","fase_id":11,"substance_slug":"saibro","municipality":"Lagoa dos Três Cantos, Tapera"},{"geometry":{"type":"Polygon","coordinates":[[[-52.939692,-28.617431,0],[-52.940526,-28.617431,0],[-52.940526,-28.617154,0],[-52.940803,-28.617154,0],[-52.940803,-28.616876,0],[-52.940526,-28.616876,0],[-52.940526,-28.616598,0],[-52.939692,-28.616598,0],[-52.939692,-28.617431,0]]],"centerPoint":[-52.94016774637581,-28.617016342790752]},"processo":"810967/2014","id":"{659BD7B8-E30D-408B-8674-11EDE95195D7}","numero":"810967","ano":"2014","area_ha":"0,84","fase":"LICENCIAMENTO","ultimo_evento":"730 - LICEN/LICENCIAMENTO AUTORIZADO PUBLICADO EM 05/12/2014","modified":"2014/12/05","titular":"Cindágua Saneamento Ambiental Ltda Epp","substancia":"SAIBRO","uso":"Construção civil","uf":"RS","fase_slug":"licenciamento","fase_id":9,"substance_slug":"saibro","municipality":"Selbach, Tapera"}]}